{
  "generated_at": "2026-03-04T12:34:22.702585+00:00",
  "signal_scores": {
    "alternate_elector_scheme": 1.0,
    "civil_service_purge_schedule_f": 1.0,
    "court_order_noncompliance": 0.3,
    "election_administration_capture": 2.0,
    "election_certification_interference": 0.0,
    "election_delay_or_cancellation": 1.0,
    "emergency_powers_expansion": 0.6,
    "independent_agency_capture": 0.0,
    "inspector_general_retaliation": 0.0,
    "judge_intimidation_campaign": 0.0,
    "jurisdiction_stripping_targeted": 1.0,
    "legislative_bypass_executive": 1.65,
    "legislative_oversight_obstruction": 0.0,
    "martial_law_or_military_language": 0.95,
    "military_domestic_political_use": 2.0,
    "opposition_ballot_exclusion": 0.0,
    "political_speech_surveillance": 0.65,
    "politicized_prosecution_opposition": 0.0,
    "press_restrictions": 1.0,
    "retaliation_architecture": 0.0,
    "security_loyalty_tests": 0.0,
    "state_election_preemption": 0.0
  }
}
